flexible_skiplist/__init__.py
flexible_skiplist/_skiplist.py
flexible_skiplist-0.1.0.dist-info/LICENCE.md
flexible_skiplist-0.1.0.dist-info/METADATA
flexible_skiplist-0.1.0.dist-info/WHEEL
flexible_skiplist-0.1.0.dist-info/top_level.txt
flexible_skiplist-0.1.0.dist-info/RECORD
